{
    "ratings": [ { "id":5, "vote": 321 }, { "id":4, "vote": 312 }, { "id":3, "vote": 231 }, { "id":2, "vote": 213 }, { "id":1, "vote": 123 } ],
    "filterPrices": [{"id":"all","filterName":"All", "rdName": "price-range-radio"},{"id":"10-dollars-below","filterName":"<=$10", "rdName": "price-range-radio"},{"id":"10-100-dollars","filterName":"$10-$100", "rdName": "price-range-radio"},{"id":"100-500-dollars","filterName":"$100-$500", "rdName": "price-range-radio"},{"id":"500-dollars-above","filterName":">=$500", "rdName": "price-range-radio"}],
    "filterCats": [{"id":"cat-all", "filterName":"All", "rdName": "category-radio"},{"id":"cat-smartTV", "filterName":"Smart TV", "rdName": "category-radio"},{"id":"cat-bag", "filterName":"Bag", "rdName": "category-radio"},{"id":"cat-shose", "filterName":"Shose", "rdName": "category-radio"},{"id":"cat-smartWatch", "filterName":"Smart Watch", "rdName": "category-radio"},{"id":"cat-iPad", "filterName":"iPad", "rdName": "category-radio"}]
}
